AUTHORS
LICENSE
MANIFEST.in
README.rst
setup.py
django_site_basics.egg-info/PKG-INFO
django_site_basics.egg-info/SOURCES.txt
django_site_basics.egg-info/dependency_links.txt
django_site_basics.egg-info/not-zip-safe
django_site_basics.egg-info/requires.txt
django_site_basics.egg-info/top_level.txt
site_basics/__init__.py
site_basics/conf.py
site_basics/middleware.py
site_basics/models.py
site_basics/tests.py
site_basics/urls.py
site_basics/views.py
site_basics/static/favicon.ico
site_basics/static/site_basics/annanta/css/blue.css
site_basics/static/site_basics/annanta/css/brown.css
site_basics/static/site_basics/annanta/css/green.css
site_basics/static/site_basics/annanta/css/grey.css
site_basics/static/site_basics/annanta/css/red.css
site_basics/static/site_basics/annanta/css/stylesheet.css
site_basics/static/site_basics/annanta/images/Thumbs.db
site_basics/static/site_basics/annanta/images/background.jpg
site_basics/static/site_basics/annanta/images/bottom.png
site_basics/static/site_basics/annanta/images/box_bg.png
site_basics/static/site_basics/annanta/images/colortab.png
site_basics/static/site_basics/annanta/images/content_bg.png
site_basics/static/site_basics/annanta/images/img-01.png
site_basics/static/site_basics/annanta/images/searchbutton_bg.png
site_basics/static/site_basics/annanta/images/searchbutton_bg_brown.png
site_basics/static/site_basics/annanta/images/searchbutton_bg_green.png
site_basics/static/site_basics/annanta/images/searchbutton_bg_grey.png
site_basics/static/site_basics/annanta/images/searchbutton_bg_red.png
site_basics/static/site_basics/annanta/images/searchfield_bg.png
site_basics/static/site_basics/annanta/images/top.png
site_basics/static/site_basics/annanta/images/twitter.png
site_basics/static/site_basics/annanta/images/socialmedia/Thumbs.db
site_basics/static/site_basics/annanta/images/socialmedia/facebook_32.png
site_basics/static/site_basics/annanta/images/socialmedia/flickr_32.png
site_basics/static/site_basics/annanta/images/socialmedia/lastfm_32.png
site_basics/static/site_basics/annanta/images/socialmedia/rss_32.png
site_basics/static/site_basics/annanta/images/socialmedia/twitter_32.png
site_basics/static/site_basics/annanta/images/socialmedia/vimeo_32.png
