Metadata-Version: 1.0
Name: django-site-basics
Version: 0.2.5
Summary: Reusable django app to handle /favicon.ico and robots.txt for your site
Home-page: https://github.com/littlepea/django-site-basics
Author: Evgeny Demchenko
Author-email: little_pea@list.ru
License: BSD
Platform: UNKNOWN
Classifier: Topic :: Internet :: WWW/HTTP :: Dynamic Content
Classifier: Intended Audience :: Developers
Classifier: Programming Language :: Python
Classifier: Programming Language :: Python :: 2.6
Classifier: Programming Language :: Python :: 2.7
Classifier: Framework :: Django
Classifier: Development Status :: 4 - Beta
Classifier: Operating System :: OS Independent
